office_word_count/__init__.py
word_counter_upchunk/__init__.py
word_counter_upchunk/counter.py
word_counter_upchunk/patterns.py
word_counter_upchunk/stats.py
word_counter_upchunk/text.py
word_counter_upchunk-1.1.1.dist-info/licenses/LICENSE
word_counter_upchunk-1.1.1.dist-info/METADATA
word_counter_upchunk-1.1.1.dist-info/WHEEL
word_counter_upchunk-1.1.1.dist-info/top_level.txt
word_counter_upchunk-1.1.1.dist-info/RECORD
