Metadata-Version: 2.4
Name: word_counter_upchunk
Version: 1.1.1
Summary: A drop-in-replacement for (discontinued) office-word-count
Author-email: Habibul Rahman Qalbi <habi6799@gmail.com>
Project-URL: Homepage, https://github.com/upchunk/office-word-count
Project-URL: Issues, https://github.com/upchunk/office-word-count/issues
Classifier: Programming Language :: Python :: 3
Classifier: Operating System :: OS Independent
Classifier: License :: OSI Approved :: MIT License
Classifier: Development Status :: 5 - Production/Stable
Requires-Python: >=3.10
License-File: LICENSE
Requires-Dist: regex
Dynamic: license-file
